Metadata-Version: 2.1
Name: yolo-to-mongo
Version: 0.8
Summary: YOLO to MongoDB
Home-page: https://github.com/hekaiyou/yolo_to_mongo
Author: Hekaiyou
Author-email: hekaiyou@qq.com
License: UNKNOWN
Platform: UNKNOWN
Classifier: Programming Language :: Python :: 3
Classifier: License :: OSI Approved :: MIT License
Classifier: Operating System :: OS Independent
Requires-Python: >=3.6
